bmimoudulTest/bmimoudulTest.py
bmimoudulTest/test.py
bmimoudulTest-0.0.0.1.dist-info/METADATA
bmimoudulTest-0.0.0.1.dist-info/WHEEL
bmimoudulTest-0.0.0.1.dist-info/top_level.txt
bmimoudulTest-0.0.0.1.dist-info/RECORD
