Metadata-Version: 2.1
Name: bmimoudulTest
Version: 0.0.0.1
Summary: My First Test Package
Home-page: https://blog.naver.com/dn3311
Author: imhyunwoo
Author-email: dn3311@naver.com
License: MIT
Platform: UNKNOWN
Requires-Python: >=3
